LICENSE
README.md
setup.py
seeta_det.egg-info/PKG-INFO
seeta_det.egg-info/SOURCES.txt
seeta_det.egg-info/dependency_links.txt
seeta_det.egg-info/requires.txt
seeta_det.egg-info/top_level.txt
seetadet/__init__.py
seetadet/core/__init__.py
seetadet/core/coordinator.py
seetadet/core/registry.py
seetadet/core/config/__init__.py
seetadet/core/config/defaults.py
seetadet/core/config/yacs.py
seetadet/core/engine/__init__.py
seetadet/core/engine/build.py
seetadet/core/engine/lr_scheduler.py
seetadet/core/engine/test_engine.py
seetadet/core/engine/train_engine.py
seetadet/core/engine/utils.py
seetadet/data/__init__.py
seetadet/data/assigners.py
seetadet/data/build.py
seetadet/data/loader.py
seetadet/data/pipelines.py
seetadet/data/transforms.py
seetadet/data/anchors/__init__.py
seetadet/data/anchors/rpn.py
seetadet/data/anchors/ssd.py
seetadet/data/datasets/__init__.py
seetadet/data/datasets/dataset.py
seetadet/data/datasets/datum.py
seetadet/data/evaluators/__init__.py
seetadet/data/evaluators/coco_evaluator.py
seetadet/data/evaluators/evaluator.py
seetadet/data/evaluators/voc_eval.py
seetadet/data/evaluators/voc_evaluator.py
seetadet/data/structures/__init__.py
seetadet/data/structures/mask.py
seetadet/data/targets/__init__.py
seetadet/data/targets/rcnn.py
seetadet/data/targets/retinanet.py
seetadet/data/targets/rpn.py
seetadet/data/targets/ssd.py
seetadet/models/__init__.py
seetadet/models/build.py
seetadet/models/backbones/__init__.py
seetadet/models/backbones/mobilenet_v2.py
seetadet/models/backbones/mobilenet_v3.py
seetadet/models/backbones/resnet.py
seetadet/models/backbones/vgg.py
seetadet/models/decoders/__init__.py
seetadet/models/decoders/retinanet.py
seetadet/models/decoders/rpn.py
seetadet/models/dense_heads/__init__.py
seetadet/models/dense_heads/retinanet.py
seetadet/models/dense_heads/rpn.py
seetadet/models/dense_heads/ssd.py
seetadet/models/detectors/__init__.py
seetadet/models/detectors/detector.py
seetadet/models/detectors/rcnn.py
seetadet/models/detectors/retinanet.py
seetadet/models/detectors/ssd.py
seetadet/models/necks/__init__.py
seetadet/models/necks/bifpn.py
seetadet/models/necks/fpn.py
